[{"id":1,"img":"img/hotel1.jpg","title":"From Wetlands To Canals And Dams Amsterdam Is Alive","text":"Travel Health Useful Medical Information For Good Health Be"},
{"id":2,"img":"img/hotel2.jpg","title":"Cost Cutting Ideas For Your Wedding","text":"Global Resorts Network Grn Putting Timeshares To Shame"},
{"id":3,"img":"img/hotel3.jpg","title":"Getting Cheap Airfare For Last Minute Travel","text":"Family Safari Vacation To The Home Of The Gods"},
{"id":4,"img":"img/hotel4.jpg","title":"New Ideas For A Low Cost Vacation On Watere","text":"Will The Democrats Be Able To Reverse The Online Gambling Ban"}]